hanriver/__init__.py
hanriver/hanriver.py
hanriver1/__init__.py
hanriver1/hanriver.py
hanriver-0.0.1.dist-info/METADATA
hanriver-0.0.1.dist-info/WHEEL
hanriver-0.0.1.dist-info/top_level.txt
hanriver-0.0.1.dist-info/RECORD
