Metadata-Version: 2.1
Name: hanriver
Version: 0.0.1
Summary: hanriver lang!!!!
Home-page: https://github.com/SOCIALPINE/hanriver-lang
Author: social_pine
Author-email: soncwnetp@gmail.com
License: MIT
Requires-Python: >=3
